buysafe/__init__.py
buysafe/admin.py
buysafe/exceptions.py
buysafe/fields.py
buysafe/forms.py
buysafe/models.py
buysafe/tests.py
buysafe/urls.py
buysafe/utils.py
buysafe/views.py
buysafe/widgets.py
buysafe/templates/buysafe/entry.html
buysafe/templates/buysafe/fail.html
buysafe/templates/buysafe/start.html
buysafe/templates/buysafe/success.html
django_buysafe-0.2.dist-info/DESCRIPTION.rst
django_buysafe-0.2.dist-info/METADATA
django_buysafe-0.2.dist-info/pydist.json
django_buysafe-0.2.dist-info/RECORD
django_buysafe-0.2.dist-info/top_level.txt
django_buysafe-0.2.dist-info/WHEEL
