Metadata-Version: 2.0
Name: django-buysafe
Version: 0.2
Summary: Django wrapper for SunTech BuySafe (TM).
Home-page: http://github.com/uranusjr/django-buysafe
Author: Tzu-ping Chung
Author-email: uranusjr@gmail.com
License: BSD License
Platform: UNKNOWN
Classifier: Environment :: Web Environment
Classifier: Framework :: Django
Classifier: Intended Audience :: Developers
Classifier: License :: OSI Approved :: BSD License
Classifier: Operating System :: OS Independent
Classifier: Programming Language :: Python
Classifier: Programming Language :: Python :: 2.6
Classifier: Programming Language :: Python :: 2.7
Classifier: Topic :: Internet :: WWW/HTTP
Classifier: Topic :: Internet :: WWW/HTTP :: Dynamic Content
Requires-Dist: django
